{
    "example_source": [
        "▁我还",
        "澄清",
        "了",
        "在该",
        "会议上",
        "提出的",
        "若干",
        "事项",
        "。"
    ],
    "example_target": [
        "<s>",
        "▁i",
        "▁was",
        "▁able",
        "▁to",
        "▁provide",
        "▁clarification",
        "▁on",
        "▁some",
        "▁of",
        "▁the",
        "▁matters",
        "▁which",
        "▁were",
        "▁raised",
        "▁at",
        "▁that",
        "▁meeting",
        ".",
        "</s>"
    ],
    "hypotheses": [
        {
            "hypothesis": [
                "▁i",
                "▁would",
                "▁also",
                "▁like",
                "▁to",
                "▁clarify",
                "▁the",
                "▁number",
                "▁of",
                "▁issues",
                "▁in",
                "▁the",
                "▁meeting",
                "▁of",
                "▁the",
                "▁meeting",
                "."
            ],
            "score": -16.287139892578125
        },
        {
            "hypothesis": [
                "▁i",
                "▁would",
                "▁also",
                "▁like",
                "▁to",
                "▁clarify",
                "▁the",
                "▁number",
                "▁of",
                "▁matters",
                "▁in",
                "▁the",
                "▁meeting",
                "▁of",
                "▁the",
                "▁meeting",
                "."
            ],
            "score": -16.29115104675293
        },
        {
            "hypothesis": [
                "▁i",
                "▁would",
                "▁also",
                "▁like",
                "▁to",
                "▁clarify",
                "▁the",
                "▁number",
                "▁of",
                "▁speakers",
                "▁in",
                "▁the",
                "▁meeting",
                "▁of",
                "▁the",
                "▁meeting",
                "."
            ],
            "score": -16.38421058654785
        },
        {
            "hypothesis": [
                "▁i",
                "▁would",
                "▁also",
                "▁like",
                "▁to",
                "▁clarify",
                "▁the",
                "▁number",
                "▁of",
                "▁speakers",
                "▁in",
                "▁the",
                "▁meeting",
                "▁of",
                "▁the",
                "▁meeting",
                "▁of",
                "▁the",
                "▁meeting",
                "."
            ],
            "score": -18.9622745513916
        },
        {
            "hypothesis": [
                "▁i",
                "▁would",
                "▁also",
                "▁like",
                "▁to",
                "▁clarify",
                "▁the",
                "▁number",
                "▁of",
                "▁matters",
                "▁in",
                "▁the",
                "▁meeting",
                "▁of",
                "▁the",
                "▁meeting",
                "▁of",
                "▁the",
                "▁meeting",
                "."
            ],
            "score": -18.995925903320312
        },
        {
            "hypothesis": [
                "▁i",
                "▁would",
                "▁also",
                "▁like",
                "▁to",
                "▁clarify",
                "▁the",
                "▁number",
                "▁of",
                "▁issues",
                "▁in",
                "▁the",
                "▁meeting",
                "▁of",
                "▁the",
                "▁conference",
                "▁on",
                "▁the",
                "▁meeting",
                "."
            ],
            "score": -19.247968673706055
        },
        {
            "hypothesis": [
                "▁i",
                "▁would",
                "▁also",
                "▁like",
                "▁to",
                "▁clarify",
                "▁the",
                "▁number",
                "▁of",
                "▁speakers",
                "▁in",
                "▁the",
                "▁meeting",
                "▁of",
                "▁the",
                "▁conference",
                "▁on",
                "▁the",
                "▁meeting",
                "."
            ],
            "score": -19.26619529724121
        },
        {
            "hypothesis": [
                "▁i",
                "▁would",
                "▁also",
                "▁like",
                "▁to",
                "▁clarify",
                "▁the",
                "▁number",
                "▁of",
                "▁matters",
                "▁in",
                "▁the",
                "▁meeting",
                "▁of",
                "▁the",
                "▁conference",
                "▁on",
                "▁the",
                "▁meeting",
                "."
            ],
            "score": -19.297901153564453
        },
        {
            "hypothesis": [
                "▁i",
                "▁would",
                "▁also",
                "▁like",
                "▁to",
                "▁clarify",
                "▁the",
                "▁number",
                "▁of",
                "▁speakers",
                "▁in",
                "▁the",
                "▁meeting",
                "▁of",
                "▁the",
                "▁conference",
                "▁on",
                "▁the",
                "▁meeting",
                "▁of",
                "▁the",
                "▁meeting",
                "."
            ],
            "score": -21.457965850830078
        },
        {
            "hypothesis": [
                "▁i",
                "▁would",
                "▁also",
                "▁like",
                "▁to",
                "▁clarify",
                "▁the",
                "▁number",
                "▁of",
                "▁speakers",
                "▁in",
                "▁the",
                "▁meeting",
                "▁of",
                "▁the",
                "▁conference",
                "▁on",
                "▁the",
                "▁meeting",
                "▁of",
                "▁the",
                "▁conference",
                "."
            ],
            "score": -22.057857513427734
        }
    ],
    "diagnostic_info": "eyJ0IjogIjIwMjQtMDktMDZUMDQ6NTY6MDMuNDI2NDI1IiwgImgiOiAiYW5kcmV3aGluaCIsICJ1IjogImFuZHJld2hpbmgifQ=="
}