{
    "example_source": [
        "▁我还",
        "澄清",
        "了",
        "在该",
        "会议上",
        "提出的",
        "若干",
        "事项",
        "。"
    ],
    "example_target": [
        "<s>",
        "▁i",
        "▁was",
        "▁able",
        "▁to",
        "▁provide",
        "▁clarification",
        "▁on",
        "▁some",
        "▁of",
        "▁the",
        "▁matters",
        "▁which",
        "▁were",
        "▁raised",
        "▁at",
        "▁that",
        "▁meeting",
        ".",
        "</s>"
    ],
    "hypotheses": [
        {
            "hypothesis": [
                "▁i",
                "▁have",
                "▁also",
                "▁clarified",
                "▁clarification",
                "▁on",
                "▁a",
                "▁number",
                "▁of",
                "▁matters",
                "▁raised",
                "▁by",
                "▁the",
                "▁conference",
                "."
            ],
            "score": -8.068081855773926
        },
        {
            "hypothesis": [
                "▁i",
                "▁have",
                "▁also",
                "▁clarified",
                "▁clarification",
                "▁on",
                "▁a",
                "▁number",
                "▁of",
                "▁matters",
                "▁raised",
                "▁by",
                "▁the",
                "▁meeting",
                "."
            ],
            "score": -8.849620819091797
        },
        {
            "hypothesis": [
                "▁i",
                "▁would",
                "▁also",
                "▁like",
                "▁to",
                "▁clarify",
                "▁a",
                "▁number",
                "▁of",
                "▁matters",
                "▁raised",
                "▁by",
                "▁the",
                "▁conference",
                "."
            ],
            "score": -8.930953025817871
        },
        {
            "hypothesis": [
                "▁i",
                "▁would",
                "▁also",
                "▁like",
                "▁to",
                "▁clarify",
                "▁a",
                "▁number",
                "▁of",
                "▁matters",
                "▁raised",
                "▁by",
                "▁the",
                "▁meeting",
                "."
            ],
            "score": -9.172181129455566
        },
        {
            "hypothesis": [
                "▁i",
                "▁should",
                "▁also",
                "▁like",
                "▁to",
                "▁clarify",
                "▁a",
                "▁number",
                "▁of",
                "▁matters",
                "▁raised",
                "▁by",
                "▁the",
                "▁conference",
                "."
            ],
            "score": -9.294564247131348
        },
        {
            "hypothesis": [
                "▁i",
                "▁would",
                "▁also",
                "▁like",
                "▁to",
                "▁clarify",
                "▁a",
                "▁number",
                "▁of",
                "▁matters",
                "▁raised",
                "▁at",
                "▁that",
                "▁meeting",
                "."
            ],
            "score": -9.39378833770752
        },
        {
            "hypothesis": [
                "▁i",
                "▁should",
                "▁also",
                "▁like",
                "▁to",
                "▁clarify",
                "▁a",
                "▁number",
                "▁of",
                "▁matters",
                "▁raised",
                "▁by",
                "▁the",
                "▁meeting",
                "."
            ],
            "score": -9.651984214782715
        },
        {
            "hypothesis": [
                "▁i",
                "▁would",
                "▁also",
                "▁like",
                "▁to",
                "▁clarify",
                "▁a",
                "▁number",
                "▁of",
                "▁matters",
                "▁submitted",
                "▁by",
                "▁the",
                "▁conference",
                "."
            ],
            "score": -9.6698579788208
        },
        {
            "hypothesis": [
                "▁i",
                "▁would",
                "▁also",
                "▁like",
                "▁to",
                "▁clarify",
                "▁a",
                "▁number",
                "▁of",
                "▁matters",
                "▁raised",
                "▁by",
                "▁the",
                "▁conference",
                "▁on",
                "▁a",
                "▁number",
                "▁of",
                "▁matters",
                "."
            ],
            "score": -10.97097110748291
        },
        {
            "hypothesis": [
                "▁i",
                "▁should",
                "▁also",
                "▁like",
                "▁to",
                "▁clarify",
                "▁a",
                "▁number",
                "▁of",
                "▁matters",
                "▁raised",
                "▁by",
                "▁the",
                "▁conference",
                "▁on",
                "▁a",
                "▁number",
                "▁of",
                "▁matters",
                "."
            ],
            "score": -11.649706840515137
        }
    ],
    "diagnostic_info": "eyJ0IjogIjIwMjQtMDktMDZUMDU6MDY6NTIuNDg0NjcwIiwgImgiOiAiYW5kcmV3aGluaCIsICJ1IjogImFuZHJld2hpbmgifQ=="
}